odoo8_addon_stock_move_backdating-8.0.1.0.0.99.dev17-nspkg.pth
odoo_addons/stock_move_backdating/README.rst
odoo_addons/stock_move_backdating/__init__.py
odoo_addons/stock_move_backdating/__openerp__.py
odoo_addons/stock_move_backdating/i18n/am.po
odoo_addons/stock_move_backdating/i18n/ca.po
odoo_addons/stock_move_backdating/i18n/de.po
odoo_addons/stock_move_backdating/i18n/es.po
odoo_addons/stock_move_backdating/i18n/es_AR.po
odoo_addons/stock_move_backdating/i18n/es_MX.po
odoo_addons/stock_move_backdating/i18n/fi.po
odoo_addons/stock_move_backdating/i18n/fr.po
odoo_addons/stock_move_backdating/i18n/gl.po
odoo_addons/stock_move_backdating/i18n/hr.po
odoo_addons/stock_move_backdating/i18n/hr_HR.po
odoo_addons/stock_move_backdating/i18n/it.po
odoo_addons/stock_move_backdating/i18n/nl.po
odoo_addons/stock_move_backdating/i18n/pt.po
odoo_addons/stock_move_backdating/i18n/pt_BR.po
odoo_addons/stock_move_backdating/i18n/pt_PT.po
odoo_addons/stock_move_backdating/i18n/ro.po
odoo_addons/stock_move_backdating/i18n/sl.po
odoo_addons/stock_move_backdating/i18n/stock_move_backdating.pot
odoo_addons/stock_move_backdating/i18n/tr.po
odoo_addons/stock_move_backdating/i18n/tr_TR.po
odoo_addons/stock_move_backdating/models/__init__.py
odoo_addons/stock_move_backdating/models/account_move.py
odoo_addons/stock_move_backdating/models/stock_move.py
odoo_addons/stock_move_backdating/static/description/icon.png
odoo_addons/stock_move_backdating/tests/__init__.py
odoo_addons/stock_move_backdating/tests/test_stock_move_backdating.py
odoo_addons/stock_move_backdating/wizards/__init__.py
odoo_addons/stock_move_backdating/wizards/stock_transfer_details.py
odoo_addons/stock_move_backdating/wizards/stock_transfer_details_view.xml
odoo8_addon_stock_move_backdating-8.0.1.0.0.99.dev17.dist-info/METADATA
odoo8_addon_stock_move_backdating-8.0.1.0.0.99.dev17.dist-info/WHEEL
odoo8_addon_stock_move_backdating-8.0.1.0.0.99.dev17.dist-info/namespace_packages.txt
odoo8_addon_stock_move_backdating-8.0.1.0.0.99.dev17.dist-info/top_level.txt
odoo8_addon_stock_move_backdating-8.0.1.0.0.99.dev17.dist-info/RECORD
